erlei/__init__.py
erlei/pipe.py
erlei/underscore.py
erlei/decorators/__init__.py
erlei/decorators/currying.py
erlei/decorators/infix.py
erlei/decorators/tailrecurve.py
erlei-1.0.0.dist-info/DESCRIPTION.rst
erlei-1.0.0.dist-info/METADATA
erlei-1.0.0.dist-info/RECORD
erlei-1.0.0.dist-info/WHEEL
erlei-1.0.0.dist-info/metadata.json
erlei-1.0.0.dist-info/top_level.txt
