Metadata-Version: 2.0
Name: erlei
Version: 1.0.0
Summary: A small python library that gives you functional programming.
Home-page: UNKNOWN
Author: CJ
Author-email: 1550490320@qq.com
License: UNKNOWN
Platform: UNKNOWN
Classifier: Programming Language :: Python :: 3
Classifier: License :: OSI Approved :: MIT License
Classifier: Operating System :: OS Independent
